bentoncounty_gistools/__init__.py
bentoncounty_gistools/bentoncounty_gistools.py
bentoncounty_gistools/maps.py
bentoncounty_gistools/template.py
bentoncounty_gistools/urls.py
bentoncounty_gistools-0.0.8.dist-info/LICENSE
bentoncounty_gistools-0.0.8.dist-info/METADATA
bentoncounty_gistools-0.0.8.dist-info/WHEEL
bentoncounty_gistools-0.0.8.dist-info/top_level.txt
bentoncounty_gistools-0.0.8.dist-info/RECORD
