Metadata-Version: 2.1
Name: bentoncounty-gistools
Version: 0.0.8
Summary: Mapping tools for Benton County Community Development, Oregon
Home-page: https://github.com/crumplecup/bentoncounty_gistools/
Author: Erik Rose
Author-email: erik.w.rose@gmail.com
License: UNKNOWN
Platform: UNKNOWN
Classifier: Programming Language :: Python :: 3.10
Classifier: License :: OSI Approved :: GNU General Public License v3 (GPLv3)
License-File: LICENSE
Requires-Dist: pip (==22.1.2)
Requires-Dist: wheel (==0.37.1)
Requires-Dist: twine (==3.6.0)
Requires-Dist: sphinx (==5.0.2)
Requires-Dist: sphinx-autoapi (==1.8.4)
Requires-Dist: sphinx-rtd-theme (==1.0.0)
Requires-Dist: pre-commit (==2.19.0)
Requires-Dist: arcgis (==2.0.0)
Requires-Dist: pipenv (==2022.7.4)
Requires-Dist: python-dotenv (==0.20.0)
